airheads/__init__.py
airheads/py.typed
airheads/schema.py
airheads-0.2.0.dist-info/METADATA
airheads-0.2.0.dist-info/WHEEL
airheads-0.2.0.dist-info/licenses/LICENSE
airheads-0.2.0.dist-info/RECORD
