Metadata-Version: 2.4
Name: airheads
Version: 0.2.0
Summary: Helper library for building social media cards, SEO tags, and head elements with air
Project-URL: Homepage, https://github.com/kentro-tech/airheads
Project-URL: Repository, https://github.com/kentro-tech/airheads
Project-URL: Issues, https://github.com/kentro-tech/airheads/issues
Author: Kentro Tech
License: MIT
License-File: LICENSE
Keywords: air,html,meta-tags,open-graph,seo,social-media,twitter-cards
Classifier: Development Status :: 3 - Alpha
Classifier: Intended Audience :: Developers
Classifier: License :: OSI Approved :: MIT License
Classifier: Programming Language :: Python :: 3
Classifier: Programming Language :: Python :: 3.13
Classifier: Topic :: Internet :: WWW/HTTP :: Dynamic Content
Classifier: Topic :: Software Development :: Libraries :: Python Modules
Requires-Python: >=3.13
Requires-Dist: air
Provides-Extra: dev
Requires-Dist: build; extra == 'dev'
Requires-Dist: pytest; extra == 'dev'
Requires-Dist: ruff; extra == 'dev'
Requires-Dist: twine; extra == 'dev'
